{
  "intents": [
      {
          "tag": "greeting",
          "patterns": [
              "Hi",
              "Hey",
              "Hello"
          ],
          "responses": [
              "Hey :-) ",
              "Hello, Thanks for visiting",
              "Hi there, What can I do for you?"
          ]
      },
      {
          "tag": "goodbye",
          "patterns": [
              "Bye",
              "Goodbye"
          ],
          "responses": [
              "See you later, thanks for visiting",
              "Have a nice day",
              "Bye! Come back again soon."
          ]
      },
      {
          "tag": "thanks",
          "patterns": [
              "Thanks",
              "Thank you"
          ],
          "responses": [
              "Happy to help!",
              "Any time!",
              "My pleasure"
          ]
      },
      {
          "tag": "funny",
          "patterns": [
              "Tell me a joke!",
              "Tell me something funny!"
          ],
          "responses": [
              "My friend was explaining electricity to me, but I was like, Watt?",
              "I failed math so many times at school, I cant even count.",
              "A book fell on my head the other day. I only have my shelf to blame though."
          ]
      },
      {
          "tag": "login_credentials",
          "patterns": [
              "New User-id and password",
              "create new account",
              "how to create new account"
          ],
          "responses": [
              "Click on Sign Up link"
          ]
      },
      {
          "tag": " forgotten password",
          "patterns": [
              "forgotten password",
              "lost my password",
              "don't remember my password",
              "lost my user_credentials",
              "lost my login id password",
              "i have forget password",
              "forget password"
          ],
          "responses": [
              "Click on forget password link to reset your password"
          ]
      },
      {
          "tag": "Invalid Credentials",
          "patterns": [
              "Invalid Username and Password is displayed",
              "shows invalid credentials",
              "can not log in through credentials"
          ],
          "responses": [
              "Recheck the login credentials. Confirm whether someone else has logged in with the same credentials ."
          ]
      },
      {
          "tag": "items",
          "patterns": [
              "Which items do you have?",
              "What kinds of items are there?",
              "What do you sell?"
          ],
          "responses": [
              "We sell Merchandises of influencers"
          ]
      },
      {
          "tag": "payments",
          "patterns": [
              "Do you take credit cards?",
              "Do you accept Mastercard?",
              "Can I pay with Paypal?",
              "Are you cash only?"
          ],
          "responses": [
              "We accept most major credit cards and online payments."
          ]
      },
      {
          "tag": "return",
          "patterns": [
              "return policy",
              "return days"
          ],
          "responses": [
              "Product should be returned in 2 weeks."
          ]
      },
      {
          "tag": "shipping ",
          "patterns": [
              "shipping cost",
              "delivery cost"
          ],
          "responses": [
              "Products above 500 has free delivery"
          ]
      },
      {
          "tag": "order",
          "patterns": [
              "how to track order",
              "order details"
          ],
          "responses": [
              "Order can be tracked through the specified section"
          ]
      },
      {
          "tag": "delivery",
          "patterns": [
              "How long does delivery take?",
              "How long does shipping take?",
              "When do I get my delivery?"
          ],
          "responses": [
              "Usually Delivery takes 2-4 days."
          ]
      }
  ]
}